{
  "objectInfo" : {
    "id" : "f3WuHBALqeChSHUSR8xia2",
    "name" : "Restv2_Kafka_JWT",
    "type" : "SIDataflow",
    "metadata" : {
      "modelVersion" : {
        "major" : 0,
        "minor" : 0
      },
      "repoInfo" : {
        "repoHandle" : "a63a9057-9840-425a-975d-d9520b0a3b74"
      },
      "contextAttributes" : [ {
        "name" : "parentId",
        "value" : "hsNYEJlb3I8hd70QNcQfG1"
      }, {
        "name" : "version",
        "value" : "2"
      } ],
      "additionalInfo" : {
        "description" : null,
        "contentType" : "Binary",
        "documentState" : "VALID"
      }
    }
  },
  "dataFileExtension" : "dat",
  "updateTime" : "2025-10-31T06:38:27.472Z",
  "objectRefs" : [ {
    "id" : "dYMW95UpEmWg6aQHZoBaER",
    "name" : "SIAutomation_Kafka_2025.07.M",
    "type" : "Connection",
    "metadata" : {
      "modelVersion" : {
        "major" : 0,
        "minor" : 0
      },
      "repoInfo" : {
        "repoHandle" : "0100030B000000000046"
      },
      "contextAttributes" : null,
      "additionalInfo" : {
        "description" : null,
        "contentType" : "JSON",
        "documentState" : "COMPLETE"
      }
    },
    "path" : "/SYS"
  }, {
    "id" : "4w4bo6o9c8sfaG9qmAxgAX",
    "name" : "invr74pam01",
    "type" : "AgentGroup",
    "metadata" : {
      "modelVersion" : {
        "major" : 0,
        "minor" : 0
      },
      "repoInfo" : {
        "repoHandle" : "01000325000000000004"
      },
      "contextAttributes" : null,
      "additionalInfo" : {
        "description" : null,
        "contentType" : "JSON",
        "documentState" : "VALID"
      }
    },
    "path" : "/SYS"
  }, {
    "id" : "3pXFHUBzjkGf7sk0VT6UyI",
    "name" : "SIAutomation_RestV2_2025.4.M",
    "type" : "Connection",
    "metadata" : {
      "modelVersion" : {
        "major" : 0,
        "minor" : 0
      },
      "repoInfo" : {
        "repoHandle" : "0100030B00000000003R"
      },
      "contextAttributes" : null,
      "additionalInfo" : {
        "description" : null,
        "contentType" : "JSON",
        "documentState" : "COMPLETE"
      }
    },
    "path" : "/SYS"
  } ],
  "readableFileExtension" : "json",
  "readableFilePresent" : true
}