{
  "objectInfo" : {
    "id" : "2qOrXKIJmoMbSER2SWpzqK",
    "name" : "Sanity 25 01 2023",
    "type" : "SIDataflow",
    "metadata" : {
      "modelVersion" : {
        "major" : 0,
        "minor" : 0
      },
      "repoInfo" : {
        "repoHandle" : "55371e88-a138-4562-bd94-ac983689be1c"
      },
      "contextAttributes" : [ {
        "name" : "parentId",
        "value" : "3z4NI046haJjU2PkLy5ncX"
      }, {
        "name" : "version",
        "value" : "2"
      } ],
      "additionalInfo" : {
        "description" : null,
        "contentType" : "Binary",
        "documentState" : "COMPLETE"
      }
    }
  },
  "dataFileExtension" : "dat",
  "objectRefs" : [ {
    "id" : "5yPLDP2TJuXb5v2J7f9NEd",
    "name" : "invu20b2b01",
    "type" : "AgentGroup",
    "metadata" : {
      "modelVersion" : {
        "major" : 0,
        "minor" : 0
      },
      "repoInfo" : {
        "repoHandle" : "01000325000000000009"
      },
      "contextAttributes" : null,
      "additionalInfo" : {
        "description" : null,
        "contentType" : "JSON",
        "documentState" : "VALID"
      }
    },
    "path" : "/SYS"
  }, {
    "id" : "auvR2NPrRE9lkJW9wt4GMo",
    "name" : "Kafka 16qa01",
    "type" : "Connection",
    "metadata" : {
      "modelVersion" : {
        "major" : 0,
        "minor" : 0
      },
      "repoInfo" : {
        "repoHandle" : "0100030B000000000014"
      },
      "contextAttributes" : null,
      "additionalInfo" : {
        "description" : null,
        "contentType" : "JSON",
        "documentState" : "COMPLETE"
      }
    },
    "path" : "/SYS"
  } ]
}