{
  "objectInfo" : {
    "id" : "cbJlkhpsjAFj88cien3rKC",
    "name" : "TailFile to eventHUB",
    "type" : "SIDataflow",
    "metadata" : {
      "modelVersion" : {
        "major" : 0,
        "minor" : 0
      },
      "repoInfo" : {
        "repoHandle" : "8a8559c6-5f0c-41f3-9384-942175bf9096"
      },
      "contextAttributes" : [ {
        "name" : "parentId",
        "value" : "30w8H71OOkSjrz9BrLTDK5"
      }, {
        "name" : "version",
        "value" : "1"
      } ],
      "additionalInfo" : {
        "description" : "Transform",
        "contentType" : "Binary",
        "documentState" : "COMPLETE"
      }
    }
  },
  "dataFileExtension" : "dat",
  "objectRefs" : [ {
    "id" : "5P8kGjikmdthGf4UzMtUaf",
    "name" : "invw19pam02",
    "type" : "AgentGroup",
    "metadata" : {
      "modelVersion" : {
        "major" : 0,
        "minor" : 0
      },
      "repoInfo" : {
        "repoHandle" : "011AND25000000000005"
      },
      "contextAttributes" : null,
      "additionalInfo" : {
        "description" : null,
        "contentType" : "JSON",
        "documentState" : "VALID"
      }
    },
    "path" : "/SYS"
  }, {
    "id" : "1wzJLlaqJF5fJAOx3izJYY",
    "name" : "azureEventHub345",
    "type" : "Connection",
    "metadata" : {
      "modelVersion" : {
        "major" : 0,
        "minor" : 0
      },
      "repoInfo" : {
        "repoHandle" : "011AND0B0000000000CA"
      },
      "contextAttributes" : null,
      "additionalInfo" : {
        "description" : null,
        "contentType" : "JSON",
        "documentState" : "COMPLETE"
      }
    },
    "path" : "/SYS"
  }, {
    "id" : "bnQyjfiIZeqbohvf02hyym",
    "name" : "SIUIAutomation_Tailfile_19thMay",
    "type" : "Connection",
    "metadata" : {
      "modelVersion" : {
        "major" : 0,
        "minor" : 0
      },
      "repoInfo" : {
        "repoHandle" : "011AND0B0000000000C9"
      },
      "contextAttributes" : null,
      "additionalInfo" : {
        "description" : null,
        "contentType" : "JSON",
        "documentState" : "COMPLETE"
      }
    },
    "path" : "/SYS"
  } ]
}