{
  "objectInfo" : {
    "id" : "4idAphbR9vnkSLRPyP0kUJ",
    "name" : "JmsToKafka_Git",
    "type" : "SIDataflow",
    "metadata" : {
      "modelVersion" : {
        "major" : 0,
        "minor" : 0
      },
      "repoInfo" : {
        "repoHandle" : "3a018dde-22d2-48c2-a664-4a06c86e7c42"
      },
      "contextAttributes" : [ {
        "name" : "parentId",
        "value" : "6nZCTU49ALVbkszlD7wZCC"
      }, {
        "name" : "version",
        "value" : "1"
      } ],
      "additionalInfo" : {
        "description" : "TestAutomation",
        "contentType" : "Binary",
        "documentState" : "COMPLETE"
      }
    }
  },
  "dataFileExtension" : "dat",
  "objectRefs" : [ {
    "id" : "729OzKmolppbfykn0YyCsv",
    "name" : "SIAutomation_Jms_r36_RE_Rhel8",
    "type" : "Connection",
    "metadata" : {
      "modelVersion" : {
        "major" : 0,
        "minor" : 0
      },
      "repoInfo" : {
        "repoHandle" : "0103UX0B0000000000KN"
      },
      "contextAttributes" : null,
      "additionalInfo" : {
        "description" : null,
        "contentType" : "JSON",
        "documentState" : "COMPLETE"
      }
    },
    "path" : "/SYS"
  }, {
    "id" : "a5Fkwiw57G7lFQbjMghXGt",
    "name" : "SIAutomation_Kafka_r39_Rhel8_PAM",
    "type" : "Connection",
    "metadata" : {
      "modelVersion" : {
        "major" : 0,
        "minor" : 0
      },
      "repoInfo" : {
        "repoHandle" : "0103UX0B0000000000H2"
      },
      "contextAttributes" : null,
      "additionalInfo" : {
        "description" : null,
        "contentType" : "JSON",
        "documentState" : "COMPLETE"
      }
    },
    "path" : "/SYS"
  }, {
    "id" : "7SpnNlbOYb2j4KoogXSIQg",
    "name" : "AgentGroup",
    "type" : "AgentGroup",
    "metadata" : {
      "modelVersion" : {
        "major" : 0,
        "minor" : 0
      },
      "repoInfo" : {
        "repoHandle" : "0103UX25000000000002"
      },
      "contextAttributes" : null,
      "additionalInfo" : {
        "description" : null,
        "contentType" : "JSON",
        "documentState" : "VALID"
      }
    },
    "path" : "/SYS"
  } ]
}