{
  "objectInfo" : {
    "id" : "a7GoT51mVgMb56Hq845iar",
    "name" : "KafkaToKafka_Git",
    "type" : "SIDataflow",
    "metadata" : {
      "modelVersion" : {
        "major" : 0,
        "minor" : 0
      },
      "repoInfo" : {
        "repoHandle" : "58d6690f-9737-4068-93b9-1b7d0d4f639a"
      },
      "contextAttributes" : [ {
        "name" : "parentId",
        "value" : "4DtClh4FcdUc70ftBZ8OyK"
      }, {
        "name" : "version",
        "value" : "1"
      } ],
      "additionalInfo" : {
        "description" : "KafkaToKafka_Git",
        "contentType" : "Binary",
        "documentState" : "COMPLETE"
      }
    }
  },
  "dataFileExtension" : "dat",
  "objectRefs" : [ {
    "id" : "dnDqLCLn4UHjbL0tOBnJAg",
    "name" : "SIAutomation_Kafka_r39_Rhel8_PAM",
    "type" : "Connection",
    "metadata" : {
      "modelVersion" : {
        "major" : 0,
        "minor" : 0
      },
      "repoInfo" : {
        "repoHandle" : "012CX30B00000000006P"
      },
      "contextAttributes" : null,
      "additionalInfo" : {
        "description" : null,
        "contentType" : "JSON",
        "documentState" : "COMPLETE"
      }
    },
    "path" : "/SYS"
  }, {
    "id" : "cKE0MQPzaspeHUslKNQKqF",
    "name" : "AgentGroup",
    "type" : "AgentGroup",
    "metadata" : {
      "modelVersion" : {
        "major" : 0,
        "minor" : 0
      },
      "repoInfo" : {
        "repoHandle" : "012CX325000000000003"
      },
      "contextAttributes" : null,
      "additionalInfo" : {
        "description" : null,
        "contentType" : "JSON",
        "documentState" : "VALID"
      }
    },
    "path" : "/SYS"
  } ]
}