{
  "objectInfo" : {
    "id" : "8yD8E3o0niRbIjHTM76KwC",
    "name" : "KinesisStreamsTokafka_Git",
    "type" : "SIDataflow",
    "metadata" : {
      "modelVersion" : {
        "major" : 0,
        "minor" : 0
      },
      "repoInfo" : {
        "repoHandle" : "95978daa-8182-4d9e-9260-1dbd466afe60"
      },
      "contextAttributes" : [ {
        "name" : "parentId",
        "value" : "6nZCTU49ALVbkszlD7wZCC"
      }, {
        "name" : "version",
        "value" : "1"
      } ],
      "additionalInfo" : {
        "description" : "KinesisStreamsTokafka_Git",
        "contentType" : "Binary",
        "documentState" : "COMPLETE"
      }
    }
  },
  "dataFileExtension" : "dat",
  "objectRefs" : [ {
    "id" : "03UG7vqevrrkn8FPnwBQkv",
    "name" : "SIAutomation_Kafka_SSL_r36_Rhel8_PAM",
    "type" : "Connection",
    "metadata" : {
      "modelVersion" : {
        "major" : 0,
        "minor" : 0
      },
      "repoInfo" : {
        "repoHandle" : "0103UX0B0000000000I3"
      },
      "contextAttributes" : null,
      "additionalInfo" : {
        "description" : null,
        "contentType" : "JSON",
        "documentState" : "COMPLETE"
      }
    },
    "path" : "/SYS"
  }, {
    "id" : "3kd5JwycXkmcW9Dvt3SEu5",
    "name" : "SIAutomation_KinesisStreams_R40",
    "type" : "Connection",
    "metadata" : {
      "modelVersion" : {
        "major" : 0,
        "minor" : 0
      },
      "repoInfo" : {
        "repoHandle" : "0103UX0B0000000000JI"
      },
      "contextAttributes" : null,
      "additionalInfo" : {
        "description" : null,
        "contentType" : "JSON",
        "documentState" : "COMPLETE"
      }
    },
    "path" : "/SYS"
  }, {
    "id" : "7SpnNlbOYb2j4KoogXSIQg",
    "name" : "AgentGroup",
    "type" : "AgentGroup",
    "metadata" : {
      "modelVersion" : {
        "major" : 0,
        "minor" : 0
      },
      "repoInfo" : {
        "repoHandle" : "0103UX25000000000002"
      },
      "contextAttributes" : null,
      "additionalInfo" : {
        "description" : null,
        "contentType" : "JSON",
        "documentState" : "VALID"
      }
    },
    "path" : "/SYS"
  } ]
}