{
  "objectInfo" : {
    "id" : "4eWwTM8WaMJdesrzNO34MS",
    "name" : "KinesisStreamsTokafka_Git",
    "type" : "SIDataflow",
    "metadata" : {
      "modelVersion" : {
        "major" : 0,
        "minor" : 0
      },
      "repoInfo" : {
        "repoHandle" : "951d3e51-f759-4bfa-b5a1-a98fc43ce7a5"
      },
      "contextAttributes" : [ {
        "name" : "parentId",
        "value" : "2QV1ETad43kfzuDBBRo7mz"
      }, {
        "name" : "version",
        "value" : "1"
      } ],
      "additionalInfo" : {
        "description" : "KinesisStreamsTokafka_Git",
        "contentType" : "Binary",
        "documentState" : "COMPLETE"
      }
    }
  },
  "dataFileExtension" : "dat",
  "objectRefs" : [ {
    "id" : "5rvbi2e6L0PhBVBF6DyLec",
    "name" : "SIAutomation_KinesisStreams",
    "type" : "Connection",
    "metadata" : {
      "modelVersion" : {
        "major" : 0,
        "minor" : 0
      },
      "repoInfo" : {
        "repoHandle" : "012CNC0B0000000000E1"
      },
      "contextAttributes" : null,
      "additionalInfo" : {
        "description" : null,
        "contentType" : "JSON",
        "documentState" : "COMPLETE"
      }
    },
    "path" : "/SYS"
  }, {
    "id" : "6dSsCKKmZ6minfoqCzaHk6",
    "name" : "AgentGroup",
    "type" : "AgentGroup",
    "metadata" : {
      "modelVersion" : {
        "major" : 0,
        "minor" : 0
      },
      "repoInfo" : {
        "repoHandle" : "012CNC2500000000000H"
      },
      "contextAttributes" : null,
      "additionalInfo" : {
        "description" : null,
        "contentType" : "JSON",
        "documentState" : "VALID"
      }
    },
    "path" : "/SYS"
  }, {
    "id" : "izpRgwc5l8AfJag9hhpeSQ",
    "name" : "SIAutomation_Kafka_SSL_r36_Rhel8_PAM",
    "type" : "Connection",
    "metadata" : {
      "modelVersion" : {
        "major" : 0,
        "minor" : 0
      },
      "repoInfo" : {
        "repoHandle" : "012CNC0B0000000000DW"
      },
      "contextAttributes" : null,
      "additionalInfo" : {
        "description" : null,
        "contentType" : "JSON",
        "documentState" : "COMPLETE"
      }
    },
    "path" : "/SYS"
  } ]
}