{
  "objectInfo" : {
    "id" : "gjnUefOy7cueX6A4TPA7KK",
    "name" : "TailFileToKafka_Git",
    "type" : "SIDataflow",
    "metadata" : {
      "modelVersion" : {
        "major" : 0,
        "minor" : 0
      },
      "repoInfo" : {
        "repoHandle" : "06cf0b6b-9764-444b-a060-15a20158e815"
      },
      "contextAttributes" : [ {
        "name" : "parentId",
        "value" : "3JqUA5ZLu0mlP7m4aZD9We"
      }, {
        "name" : "version",
        "value" : "1"
      } ],
      "additionalInfo" : {
        "description" : "TailFileToKafka_Git",
        "contentType" : "Binary",
        "documentState" : "COMPLETE"
      }
    }
  },
  "dataFileExtension" : "dat",
  "objectRefs" : [ {
    "id" : "hmJLmmdQogljkSMiukHIIH",
    "name" : "invr83pam26",
    "type" : "AgentGroup",
    "metadata" : {
      "modelVersion" : {
        "major" : 0,
        "minor" : 0
      },
      "repoInfo" : {
        "repoHandle" : "011ZFB2500000000000J"
      },
      "contextAttributes" : null,
      "additionalInfo" : {
        "description" : null,
        "contentType" : "JSON",
        "documentState" : "VALID"
      }
    },
    "path" : "/SYS"
  }, {
    "id" : "eRnCorHG3q2cN3p71m8D0m",
    "name" : "SIAutomation_Tailfile_r36_RE",
    "type" : "Connection",
    "metadata" : {
      "modelVersion" : {
        "major" : 0,
        "minor" : 0
      },
      "repoInfo" : {
        "repoHandle" : "011ZFB0B00000000004P"
      },
      "contextAttributes" : null,
      "additionalInfo" : {
        "description" : null,
        "contentType" : "JSON",
        "documentState" : "COMPLETE"
      }
    },
    "path" : "/SYS"
  }, {
    "id" : "3uyyHzXEBA7dQkvffhA8iA",
    "name" : "SIAutomation_Kafka_16qa01kafka",
    "type" : "Connection",
    "metadata" : {
      "modelVersion" : {
        "major" : 0,
        "minor" : 0
      },
      "repoInfo" : {
        "repoHandle" : "011ZFB0B0000000000KL"
      },
      "contextAttributes" : null,
      "additionalInfo" : {
        "description" : null,
        "contentType" : "JSON",
        "documentState" : "COMPLETE"
      }
    },
    "path" : "/SYS"
  } ]
}