{
  "objectInfo" : {
    "id" : "92CPSDMzY6tdbBMTUFvhym",
    "name" : "KafkaToKafkaWithFormatConverterWithJSON with Combiner - Copy 1 - Copy 1",
    "type" : "SIDataflow",
    "metadata" : {
      "modelVersion" : {
        "major" : 0,
        "minor" : 0
      },
      "repoInfo" : {
        "repoHandle" : "d3185b39-31b4-45ac-82a9-a4a01eacd8bc"
      },
      "contextAttributes" : [ {
        "name" : "parentId",
        "value" : "1fczCQsF3agfOK68iuY9oV"
      }, {
        "name" : "version",
        "value" : "1"
      } ],
      "additionalInfo" : {
        "description" : "edited",
        "contentType" : null,
        "documentState" : "COMPLETE"
      }
    }
  },
  "dataFileExtension" : "dat",
  "objectRefs" : [ {
    "id" : "8gNNE8fYnazh70PiebPCqE",
    "name" : "rhelprodval1",
    "type" : "AgentGroup",
    "metadata" : {
      "modelVersion" : {
        "major" : 0,
        "minor" : 0
      },
      "repoInfo" : {
        "repoHandle" : "011ZFB2500000000000C"
      },
      "contextAttributes" : null,
      "additionalInfo" : {
        "description" : null,
        "contentType" : "JSON",
        "documentState" : "VALID"
      }
    },
    "path" : "/SYS"
  }, {
    "id" : "8MljOciO5nOgR8bdsq9fW1",
    "name" : "kafkaConnectionSai",
    "type" : "Connection",
    "metadata" : {
      "modelVersion" : {
        "major" : 0,
        "minor" : 0
      },
      "repoInfo" : {
        "repoHandle" : "011ZFB0B000000000038"
      },
      "contextAttributes" : null,
      "additionalInfo" : {
        "description" : null,
        "contentType" : "JSON",
        "documentState" : "COMPLETE"
      }
    },
    "path" : "/SYS"
  } ]
}