{
  "objectInfo" : {
    "id" : "dIFHfwzMQCUltzhbcykhKe",
    "name" : "Saudi_Rollover_Combiner",
    "type" : "SIDataflow",
    "metadata" : {
      "modelVersion" : {
        "major" : 0,
        "minor" : 0
      },
      "repoInfo" : {
        "repoHandle" : "eedac070-1632-4281-9245-7db708062571"
      },
      "contextAttributes" : [ {
        "name" : "parentId",
        "value" : "i2MVKB69McJlEMGoLq6JuT"
      }, {
        "name" : "version",
        "value" : "1"
      } ],
      "additionalInfo" : {
        "description" : null,
        "contentType" : "Binary",
        "documentState" : "VALID"
      }
    }
  },
  "dataFileExtension" : "dat",
  "updateTime" : "2025-01-18T08:35:14.041Z",
  "objectRefs" : [ {
    "id" : "hWHL6n5ahWmdCuN4Rvk0oa",
    "name" : "AgentGroup",
    "type" : "AgentGroup",
    "metadata" : {
      "modelVersion" : {
        "major" : 0,
        "minor" : 0
      },
      "repoInfo" : {
        "repoHandle" : "0113OO25000000000004"
      },
      "contextAttributes" : null,
      "additionalInfo" : {
        "description" : null,
        "contentType" : "JSON",
        "documentState" : "VALID"
      }
    },
    "path" : "/SYS"
  }, {
    "id" : "aAoETf0JHaqfHVbqM2ZnIP",
    "name" : "SIAutomation_Kafka_2024.08.S",
    "type" : "Connection",
    "metadata" : {
      "modelVersion" : {
        "major" : 0,
        "minor" : 0
      },
      "repoInfo" : {
        "repoHandle" : "0113OO0B00000000007U"
      },
      "contextAttributes" : null,
      "additionalInfo" : {
        "description" : null,
        "contentType" : "JSON",
        "documentState" : "COMPLETE"
      }
    },
    "path" : "/SYS"
  }, {
    "id" : "jrkl0f7IwU5lP7dUosUHeJ",
    "name" : "SIAutomation_ADLSGen2_2023.04.M",
    "type" : "Connection",
    "metadata" : {
      "modelVersion" : {
        "major" : 0,
        "minor" : 0
      },
      "repoInfo" : {
        "repoHandle" : "0113OO0B00000000006X"
      },
      "contextAttributes" : null,
      "additionalInfo" : {
        "description" : null,
        "contentType" : "JSON",
        "documentState" : "COMPLETE"
      }
    },
    "path" : "/SYS"
  } ],
  "readableFileExtension" : null,
  "readableFilePresent" : false
}