{
  "objectInfo" : {
    "id" : "ateOwXp3yOKl27APJN110k",
    "name" : "2023.02.S",
    "type" : "Project",
    "metadata" : {
      "modelVersion" : {
        "major" : 0,
        "minor" : 0
      },
      "repoInfo" : null,
      "contextAttributes" : [ ],
      "additionalInfo" : {
        "description" : "",
        "contentType" : "Binary",
        "documentState" : "COMPLETE"
      }
    }
  },
  "dataFileExtension" : "json",
  "updateTime" : "2024-10-14T11:45:44.252Z",
  "objectRefs" : [ ]
}